{
    "Autorizações": {
        "Requisições": 10461.0,
        "Degradação": 0,
        "Indisponibilidade": 0
    },
    "Contas Médicas": {
        "Requisições": 401869.0,
        "Degradação": 0,
        "Indisponibilidade": 0
    },
    "Integrações-Internas": {
        "Requisições": 260165.0,
        "Degradação": 0,
        "Indisponibilidade": 0
    },
    "Integrações-Portais": {
        "Requisições": 244311.0,
        "Degradação": 0,
        "Indisponibilidade": 0
    },
    "Relatórios": {
        "Requisições": 0,
        "Degradação": 0,
        "Indisponibilidade": 0
    },
    "Integrações-TISS": {
        "Requisições": 0,
        "Degradação": 0,
        "Indisponibilidade": 0
    },
    "Site Administrativo": {
        "Requisições": 0,
        "Degradação": 0,
        "Indisponibilidade": 0
    },
    "Serviços WCF": {
        "Requisições": 0,
        "Degradação": 0,
        "Indisponibilidade": 0
    },
    "Portal do Corretor": {
        "Requisições": 0,
        "Degradação": 0,
        "Indisponibilidade": 0
    },
    "API Corretora Digital": {
        "Requisições": 0,
        "Degradação": 0,
        "Indisponibilidade": 0
    },
    "Administrativo – Chamadas aos serviços WCF": {
        "Requisições": 0,
        "Degradação": 0,
        "Indisponibilidade": 0
    },
    "Portal do Corretor – Chamadas aos serviços WCF": {
        "Requisições": 0,
        "Degradação": 0,
        "Indisponibilidade": 0
    },
    "Serviços – Chamadas a serviços externos": {
        "Requisições": 0,
        "Degradação": 0,
        "Indisponibilidade": 0
    },
    "API Corretora Digital – Chamadas aos serviços WCF": {
        "Requisições": 0,
        "Degradação": 0,
        "Indisponibilidade": 0
    },
    "Previdência PF": {
        "Requisições": 71348.0,
        "Degradação": 110.0,
        "Indisponibilidade": 0
    },
    "Financeiro PF": {
        "Requisições": 25035.0,
        "Degradação": 0,
        "Indisponibilidade": 0
    },
    "Previdência": {
        "Requisições": 23645.0,
        "Degradação": 0,
        "Indisponibilidade": 3.0
    },
    "(ANS) Saúde": {
        "Requisições": 28700.0,
        "Degradação": 0,
        "Indisponibilidade": 0
    },
    "(ANS) Odonto": {
        "Requisições": 23838.0,
        "Degradação": 0,
        "Indisponibilidade": 0
    },
    "DEO - Seguro Responsabilidade Civil": {
        "Requisições": 24468.0,
        "Degradação": 0,
        "Indisponibilidade": 0
    },
    "Empresarial": {
        "Requisições": 23455.0,
        "Degradação": 0,
        "Indisponibilidade": 0
    },
    "Empresarial - Legado": {
        "Requisições": 23314.0,
        "Degradação": 0,
        "Indisponibilidade": 0
    },
    "Residencial": {
        "Requisições": 33163.0,
        "Degradação": 0,
        "Indisponibilidade": 15.0
    },
    "Residencial - Legado": {
        "Requisições": 23318.0,
        "Degradação": 0,
        "Indisponibilidade": 0
    },
    "RCPSI - Seguro Responsabilidade Civil Individual": {
        "Requisições": 24898.0,
        "Degradação": 0,
        "Indisponibilidade": 0
    },
    "RCPSI - Seguro Responsabilidade Civil Individual - Legado": {
        "Requisições": 23305.0,
        "Degradação": 0,
        "Indisponibilidade": 0
    },
    "RCPSO - Seguro Responsabilidade Civil Coletivo - Legado": {
        "Requisições": 23290.0,
        "Degradação": 0,
        "Indisponibilidade": 0
    },
    "API SAUDE": {
        "Requisições": 2033861.0,
        "Degradação": 11557.0,
        "Indisponibilidade": 3.0
    },
    "API ODONTO": {
        "Requisições": 823314.0,
        "Degradação": 5756.0,
        "Indisponibilidade": 67.0
    },
    "API SIEBEL": {
        "Requisições": 188566.0,
        "Degradação": 17275.0,
        "Indisponibilidade": 57.0
    },
    "API JOKER": {
        "Requisições": 22262.0,
        "Degradação": 17281.0,
        "Indisponibilidade": 0
    },
    "API VIDA": {
        "Requisições": 39963.0,
        "Degradação": 14542.0,
        "Indisponibilidade": 33.0
    },
    "API PREV": {
        "Requisições": 26664.0,
        "Degradação": 11518.0,
        "Indisponibilidade": 0
    },
    "API RE": {
        "Requisições": 110430.0,
        "Degradação": 0,
        "Indisponibilidade": 0
    },
    "API BASE21": {
        "Requisições": 145919.0,
        "Degradação": 13.0,
        "Indisponibilidade": 3106.0
    },
    "API GEM": {
        "Requisições": 13256.0,
        "Degradação": 11515.0,
        "Indisponibilidade": 58.0
    },
    "Cotação": {
        "Requisições": 0,
        "Degradação": 0,
        "Indisponibilidade": 0
    },
    "Área Cliente": {
        "Requisições": 0,
        "Degradação": 0,
        "Indisponibilidade": 0
    },
    "Autenticação": {
        "Requisições": 0,
        "Degradação": 0,
        "Indisponibilidade": 0
    },
    "Layouts": {
        "Requisições": 0,
        "Degradação": 0,
        "Indisponibilidade": 0
    },
    "Proposta": {
        "Requisições": 0,
        "Degradação": 0,
        "Indisponibilidade": 0
    },
    "Transmissão": {
        "Requisições": 0,
        "Degradação": 0,
        "Indisponibilidade": 0
    },
    "Autenticação em Sistemas (SSO-PRD)": {
        "Requisições": 56775.0,
        "Degradação": 34672.0,
        "Indisponibilidade": 0
    },
    "Token URL do Frame": {
        "Requisições": 20916.0,
        "Degradação": 0,
        "Indisponibilidade": 0
    },
    "Token URL Sinistro online Vida": {
        "Requisições": 32.0,
        "Degradação": 0,
        "Indisponibilidade": 0
    },
    "Criação/Atualização de Estipulante": {
        "Requisições": 104.0,
        "Degradação": 0,
        "Indisponibilidade": 0
    },
    "Criação/Atualização de corretor": {
        "Requisições": 44.0,
        "Degradação": 0,
        "Indisponibilidade": 0
    },
    "Gerar PDF Dirf": {
        "Requisições": 0,
        "Degradação": 0,
        "Indisponibilidade": 0
    },
    "Gerar Token Core": {
        "Requisições": 2.0,
        "Degradação": 0,
        "Indisponibilidade": 0
    },
    "Token URL do Sinistro Online Patrimonial": {
        "Requisições": 32.0,
        "Degradação": 0,
        "Indisponibilidade": 0
    },
    "Dados Segurados Odonto": {
        "Requisições": 999849.0,
        "Degradação": 57586.0,
        "Indisponibilidade": 0
    },
    "Dados Segurados Previdencia": {
        "Requisições": 71348.0,
        "Degradação": 110.0,
        "Indisponibilidade": 0
    },
    "Dados Segurados Vida": {
        "Requisições": 90957.0,
        "Degradação": 9583.0,
        "Indisponibilidade": 14.0
    },
    "Dados Segurados RE": {
        "Requisições": 38771.0,
        "Degradação": 128.0,
        "Indisponibilidade": 0
    },
    "Dados Segurados Saúde": {
        "Requisições": 120284.0,
        "Degradação": 11520.0,
        "Indisponibilidade": 179.0
    },
    "Protocolo ANS": {
        "Requisições": 36721.0,
        "Degradação": 118.0,
        "Indisponibilidade": 0
    },
    "EMPRE": {
        "Requisições": 561.0,
        "Degradação": 0,
        "Indisponibilidade": 3.0
    },
    "GERAL": {
        "Requisições": 518.0,
        "Degradação": 0,
        "Indisponibilidade": 0
    },
    "RCP": {
        "Requisições": 4405.0,
        "Degradação": 0,
        "Indisponibilidade": 1.0
    },
    "RESID": {
        "Requisições": 892.0,
        "Degradação": 0,
        "Indisponibilidade": 1.0
    },
    "POST /produto/apolice": {
        "Requisições": 102.0,
        "Degradação": 18.0,
        "Indisponibilidade": 0
    },
    "Portal Empresa": {
        "Requisições": 2142.0,
        "Degradação": 0,
        "Indisponibilidade": 0
    },
    "Portal Segurado": {
        "Requisições": 958909.0,
        "Degradação": 0,
        "Indisponibilidade": 0
    },
    "Portal Dentista": {
        "Requisições": 0,
        "Degradação": 0,
        "Indisponibilidade": 0
    },
    "Top Dental": {
        "Requisições": 0,
        "Degradação": 0,
        "Indisponibilidade": 0
    },
    "movimentacao-cadastral": {
        "Requisições": 0,
        "Degradação": 0,
        "Indisponibilidade": 0
    },
    "token-corporativo": {
        "Requisições": 23556.0,
        "Degradação": 23050.0,
        "Indisponibilidade": 0
    },
    "Consulta de Segurados": {
        "Requisições": 7298.0,
        "Degradação": 0,
        "Indisponibilidade": 19.0
    },
    "Emissão de Endosso": {
        "Requisições": 336.0,
        "Degradação": 0,
        "Indisponibilidade": 0
    },
    "Consulta Apolice": {
        "Requisições": 10035.0,
        "Degradação": 0,
        "Indisponibilidade": 23.0
    },
    "Consulta de proposta por segurado": {
        "Requisições": 3433.0,
        "Degradação": 0,
        "Indisponibilidade": 0
    },
    "Consulta beneficiários por sinistro": {
        "Requisições": 132.0,
        "Degradação": 0,
        "Indisponibilidade": 0
    },
    "Liberação de pagamento sinistro (Webservice)": {
        "Requisições": 4.0,
        "Degradação": 0,
        "Indisponibilidade": 0
    },
    "Consulta de sinistro por endosso": {
        "Requisições": 4006.0,
        "Degradação": 0,
        "Indisponibilidade": 0
    }
}